iotanbo_py_utils/__init__.py
iotanbo_py_utils/__main__.py
iotanbo_py_utils/error.py
iotanbo_py_utils/file_utils.py
iotanbo_py_utils/platform.py
iotanbo_py_utils/py.typed
iotanbo_py_utils/shell_utils.py
iotanbo_py_utils-0.9.1.dist-info/entry_points.txt
iotanbo_py_utils-0.9.1.dist-info/LICENSE.rst
iotanbo_py_utils-0.9.1.dist-info/WHEEL
iotanbo_py_utils-0.9.1.dist-info/METADATA
iotanbo_py_utils-0.9.1.dist-info/RECORD
