Metadata-Version: 2.1
Name: iotanbo-py-utils
Version: 0.9.1
Summary: Python utilities by iotanbo
Home-page: https://github.com/iotanbo/iotanbo_py_utils
License: MIT
Author: iotanbo
Author-email: yurizappo@gmail.com
Requires-Python: >=3.8.0,<4.0.0
Classifier: License :: OSI Approved :: MIT License
Classifier: Programming Language :: Python :: 3
Classifier: Programming Language :: Python :: 3.8
Classifier: Programming Language :: Python :: 3.9
Requires-Dist: click (>=7.0,<8.0)
Requires-Dist: pathvalidate (>=2.4.1,<3.0.0)
Requires-Dist: result (>=0.6.0,<0.7.0)
Project-URL: Changelog, https://github.com/iotanbo/iotanbo_py_utils/releases
Project-URL: Documentation, https://iotanbo_py_utils.readthedocs.io
Project-URL: Repository, https://github.com/iotanbo/iotanbo_py_utils
